agentunit/__init__.py
agentunit/adapters/__init__.py
agentunit/adapters/agentops_adapter.py
agentunit/adapters/anthropic_bedrock.py
agentunit/adapters/autogen.py
agentunit/adapters/autogen_ag2.py
agentunit/adapters/base.py
agentunit/adapters/crewai.py
agentunit/adapters/haystack.py
agentunit/adapters/langgraph.py
agentunit/adapters/langsmith_adapter.py
agentunit/adapters/llama_index.py
agentunit/adapters/mistral_server.py
agentunit/adapters/openai_agents.py
agentunit/adapters/openai_swarm.py
agentunit/adapters/phidata.py
agentunit/adapters/promptflow.py
agentunit/adapters/rasa.py
agentunit/adapters/registry.py
agentunit/adapters/semantic_kernel.py
agentunit/adapters/swarm_adapter.py
agentunit/adapters/wandb_adapter.py
agentunit/benchmarks/__init__.py
agentunit/benchmarks/arena.py
agentunit/benchmarks/gaia.py
agentunit/benchmarks/leaderboard.py
agentunit/benchmarks/runner.py
agentunit/cli/__init__.py
agentunit/cli.py
agentunit/collaboration/__init__.py
agentunit/collaboration/branch.py
agentunit/collaboration/hub.py
agentunit/collaboration/merge.py
agentunit/collaboration/tracking.py
agentunit/collaboration/version.py
agentunit/comparison/__init__.py
agentunit/comparison/comparator.py
agentunit/comparison/reports.py
agentunit/comparison/statistics.py
agentunit/core/__init__.py
agentunit/core/exceptions.py
agentunit/core/replay.py
agentunit/core/runner.py
agentunit/core/scenario.py
agentunit/core/trace.py
agentunit/dashboard/__init__.py
agentunit/dashboard/app.py
agentunit/dashboard/components.py
agentunit/dashboard/server.py
agentunit/datasets/__init__.py
agentunit/datasets/base.py
agentunit/datasets/builtins.py
agentunit/datasets/registry.py
agentunit/examples/__init__.py
agentunit/examples/template_project/agent.py
agentunit/examples/template_project/suite.py
agentunit/generators/__init__.py
agentunit/generators/augmentation.py
agentunit/generators/llm_generator.py
agentunit/generators/templates.py
agentunit/metrics/__init__.py
agentunit/metrics/base.py
agentunit-0.6.0.dist-info/METADATA
agentunit-0.6.0.dist-info/WHEEL
agentunit-0.6.0.dist-info/entry_points.txt
agentunit-0.6.0.dist-info/licenses/LICENSE
agentunit-0.6.0.dist-info/RECORD
