Metadata-Version: 2.4
Name: agentunit
Version: 0.6.0
Summary: Pytest-style evaluation harness for agentic AI and RAG workflows
License: MIT
License-File: LICENSE
Keywords: agents,evaluation,rag,testing,otel
Author: AgentUnit Contributors
Author-email: opensource@agentunit.dev
Requires-Python: >=3.10,<4.0
Classifier: Development Status :: 3 - Alpha
Classifier: Intended Audience :: Developers
Classifier: License :: OSI Approved :: MIT License
Classifier: Programming Language :: Python :: 3
Classifier: Programming Language :: Python :: 3.10
Classifier: Programming Language :: Python :: 3.11
Classifier: Programming Language :: Python :: 3.12
Classifier: Programming Language :: Python :: 3.13
Classifier: Programming Language :: Python :: 3.14
Classifier: Topic :: Scientific/Engineering :: Artificial Intelligence
Classifier: Topic :: Software Development :: Testing
Requires-Dist: crewai (>=0.201.1,<0.202.0) ; python_version < "3.14"
Requires-Dist: httpx (>=0.27.0,<0.28.0)
Requires-Dist: huggingface-hub (>=0.21.4,<0.22.0)
Requires-Dist: langgraph (>=1.0.0a4,<2.0.0)
Requires-Dist: numpy (>=1.24.0,<2.0.0)
Requires-Dist: opentelemetry-api (>=1.25.0,<2.0.0)
Requires-Dist: opentelemetry-exporter-otlp (>=1.25.0,<2.0.0)
Requires-Dist: opentelemetry-sdk (>=1.25.0,<2.0.0)
Requires-Dist: pyyaml (>=6.0,<7.0)
Requires-Dist: ragas (>=0.1.9,<0.2.0)
Requires-Dist: rich (>=13.7.1,<14.0.0)
Requires-Dist: scipy (>=1.11.0,<2.0.0)
Project-URL: Changelog, https://github.com/aviralgarg05/agentunit/releases
Project-URL: Documentation, https://github.com/aviralgarg05/agentunit/tree/main/docs
Project-URL: Homepage, https://github.com/aviralgarg05/agentunit
Project-URL: Issue Tracker, https://github.com/aviralgarg05/agentunit/issues
Project-URL: Repository, https://github.com/aviralgarg05/agentunit
